pipeglow/__init__.py
pipeglow/__main__.py
pipeglow/cli.py
pipeglow/gitlab_api.py
pipeglow/govee_api.py
pipeglow/utils.py
pipeglow-0.0.975.dist-info/METADATA
pipeglow-0.0.975.dist-info/WHEEL
pipeglow-0.0.975.dist-info/entry_points.txt
pipeglow-0.0.975.dist-info/licenses/LICENSE
pipeglow-0.0.975.dist-info/RECORD
