Metadata-Version: 2.4
Name: pipeglow
Version: 0.0.975
Summary: ✨ Change smart lights based on CI pipeline status
Project-URL: Homepage, https://gitlab.com/brie/pipeglow
Author: Brie Carranza
License: MIT
License-File: LICENSE
Classifier: Development Status :: 3 - Alpha
Classifier: Intended Audience :: Developers
Classifier: License :: OSI Approved :: MIT License
Classifier: Programming Language :: Python
Classifier: Programming Language :: Python :: 3
Classifier: Programming Language :: Python :: 3 :: Only
Classifier: Programming Language :: Python :: 3.9
Classifier: Programming Language :: Python :: 3.10
Classifier: Programming Language :: Python :: 3.11
Classifier: Programming Language :: Python :: 3.12
Classifier: Programming Language :: Python :: 3.13
Classifier: Topic :: Internet
Classifier: Topic :: Software Development :: Build Tools
Classifier: Topic :: System :: Monitoring
Classifier: Topic :: Utilities
Requires-Python: >=3.9
Requires-Dist: certifi==2024.12.14
Requires-Dist: charset-normalizer==3.4.1
Requires-Dist: click==8.1.8
Requires-Dist: emoji==2.14.1
Requires-Dist: idna==3.10
Requires-Dist: python-dotenv==1.0.1
Requires-Dist: python-gitlab==5.3.1
Requires-Dist: requests-toolbelt==1.0.0
Requires-Dist: requests==2.32.3
Requires-Dist: urllib3==2.3.0
Provides-Extra: test
Requires-Dist: pytest; extra == 'test'
